{
    "contacts": [
        {
            "body1": 7,
            "body2": 21,
            "contact_type": 0,
            "geom1": 9,
            "geom2": 20,
            "local_pos1": [
                0.07614855702060568,
                0.004856881059524684,
                -0.01920690530043912
            ],
            "local_pos2": [
                1.1419021596500145,
                -0.16211458012276614,
                0.5999999999999996
            ]
        },
        {
            "body1": -1,
            "body2": -1,
            "contact_type": 0,
            "geom1": -1,
            "geom2": -1,
            "local_pos1": [
                0.030417957039213017,
                0.02456818585452153,
                -0.008435172397631252
            ],
            "local_pos2": [
                0.991171536416927,
                -0.24713942296850488,
                0.5999999999999996
            ]
        },
        {
            "body1": 12,
            "body2": 21,
            "contact_type": 0,
            "geom1": 12,
            "geom2": 20,
            "local_pos1": [
                0.10453578187790769,
                -0.007905736736942472,
                -0.019540556433931995
            ],
            "local_pos2": [
                1.0858373239520875,
                0.2521716835914294,
                0.5999999999999996
            ]
        },
        {
            "body1": -1,
            "body2": -1,
            "contact_type": 0,
            "geom1": -1,
            "geom2": -1,
            "local_pos1": [
                0.03651470838192317,
                0.010910212199174596,
                -0.012150857646833657
            ],
            "local_pos2": [
                1.054549537344156,
                0.30171585618063235,
                0.5999999999999996
            ]
        },
        {
            "body1": -1,
            "body2": -1,
            "contact_type": 0,
            "geom1": -1,
            "geom2": -1,
            "local_pos1": [
                0.0,
                0.0,
                0.0
            ],
            "local_pos2": [
                0.0,
                0.0,
                0.0
            ]
        }
    ],
    "facing_target": [],
    "name": "CIO_climb_5",
    "success_sustain_time": 2.0,
    "target_distance_tolerance": 0.1,
    "time_limit": 5.0,
    "weight": {
        "COM Feet XY": 0.0,
        "CoM Vel.": 0.0,
        "Contact": 80.0,
        "Control": 0.1,
        "Facing Dir": 0.0,
        "Head Height": 99.0,
        "Joint Vel.": 0.01,
        "Knee Feet XY": 0.0,
        "LFoot Up": 54.0,
        "Pelvis Up": 0.0,
        "RFoot Up": 54.0,
        "Torso Height": 100.0,
        "Torso Up": 0.0
    }
}
